indexedconv/__init__.py
indexedconv/utils.py
indexedconv/version.py
indexedconv/engine/__init__.py
indexedconv/engine/indexed.py
indexedconv/engine/masked.py
indexedconv/nets/__init__.py
indexedconv/nets/aid.py
indexedconv/nets/cifar.py
indexedconv/nets/mnist.py
IndexedConv-1.3.2.dist-info/LICENSE
IndexedConv-1.3.2.dist-info/METADATA
IndexedConv-1.3.2.dist-info/WHEEL
IndexedConv-1.3.2.dist-info/top_level.txt
IndexedConv-1.3.2.dist-info/RECORD
