Metadata-Version: 2.1
Name: IndexedConv
Version: 1.3.2
Summary: An implementation of indexed convolution and pooling
Home-page: https://github.com/IndexedConv/IndexedConv
Author: M. Jacquemont, T. Vuillaume, L. Antiga
Author-email: jacquemont@lapp.in2p3.fr
License: MIT
Classifier: Programming Language :: Python :: 3
Classifier: License :: OSI Approved :: MIT License
Classifier: Operating System :: OS Independent
License-File: LICENSE
Requires-Dist: torch (>=1.7)
Requires-Dist: torchvision
Requires-Dist: numpy
Requires-Dist: matplotlib
Requires-Dist: h5py
